ovsportranges.py
ovsportranges-0.1.2.dist-info/DESCRIPTION.rst
ovsportranges-0.1.2.dist-info/LICENSE.txt
ovsportranges-0.1.2.dist-info/METADATA
ovsportranges-0.1.2.dist-info/RECORD
ovsportranges-0.1.2.dist-info/WHEEL
ovsportranges-0.1.2.dist-info/metadata.json
ovsportranges-0.1.2.dist-info/top_level.txt
