Metadata-Version: 2.0
Name: ovsportranges
Version: 0.1.2
Summary: OVS bitwise port/mask ranges
Home-page: https://github.com/Braintrace/ovsportranges
Author: James Anderson
Author-email: janderson@braintrace.com
License: MIT
Keywords: openflow port ranges ovs ofctl
Platform: UNKNOWN
Classifier: Development Status :: 4 - Beta
Classifier: Environment :: OpenStack
Classifier: Natural Language :: English
Classifier: Operating System :: OS Independent
Classifier: Intended Audience :: Information Technology
Classifier: Topic :: System :: Networking
Classifier: License :: OSI Approved :: MIT License
Classifier: Programming Language :: Python :: 2.7
Classifier: Programming Language :: Python :: 3
Requires-Python: >2.7
